[
  {
    "dataset": "communities_crime",
    "mechanism": "NONE",
    "rate": 0,
    "results": {
      "ridge_regression": {
        "mae": 0.15789988098537183,
        "rmse": 0.2059467445092666,
        "r2": 0.40958889197672865
      },
      "random_forest": {
        "mae": 0.10867802203067528,
        "rmse": 0.1433880786939234,
        "r2": 0.7137992626901062
      }
    }
  },
  {
    "dataset": "communities_crime",
    "mechanism": "MCAR",
    "rate": 0.01,
    "results": {
      "simple": {
        "ridge_regression": {
          "mae": 0.16970314634151085,
          "rmse": 0.21150757147174176,
          "r2": 0.3772747228290725
        },
        "random_forest": {
          "mae": 0.10879658508726256,
          "rmse": 0.14066831703746785,
          "r2": 0.7245535114020463
        }
      },
      "iterative": {
        "ridge_regression": {
          "mae": 0.15702823214885814,
          "rmse": 0.20309865453158646,
          "r2": 0.42580586800736675
        },
        "random_forest": {
          "mae": 0.1096720077098219,
          "rmse": 0.14487547023288833,
          "r2": 0.7078308383478313
        }
      }
    }
  },
  {
    "dataset": "communities_crime",
    "mechanism": "MCAR",
    "rate": 0.05,
    "results": {
      "simple": {
        "ridge_regression": {
          "mae": 0.1767105208291193,
          "rmse": 0.22348357307833291,
          "r2": 0.30475820883361204
        },
        "random_forest": {
          "mae": 0.11194663080088692,
          "rmse": 0.14646198919400397,
          "r2": 0.7013967613661822
        }
      },
      "iterative": {
        "ridge_regression": {
          "mae": 0.14600309242082632,
          "rmse": 0.19151580868376764,
          "r2": 0.4894316206097875
        },
        "random_forest": {
          "mae": 0.10900590561602239,
          "rmse": 0.1443431460950356,
          "r2": 0.7099739611675614
        }
      }
    }
  },
  {
    "dataset": "communities_crime",
    "mechanism": "MCAR",
    "rate": 0.1,
    "results": {
      "simple": {
        "ridge_regression": {
          "mae": 0.15779251906695158,
          "rmse": 0.19248894536428707,
          "r2": 0.4842298032340693
        },
        "random_forest": {
          "mae": 0.1192199264546477,
          "rmse": 0.15855739394275248,
          "r2": 0.650040606314767
        }
      },
      "iterative": {
        "ridge_regression": {
          "mae": 0.14917919466204022,
          "rmse": 0.18976295146755015,
          "r2": 0.4987348517424276
        },
        "random_forest": {
          "mae": 0.11289307287942857,
          "rmse": 0.15017312918833697,
          "r2": 0.6860726760889456
        }
      }
    }
  },
  {
    "dataset": "communities_crime",
    "mechanism": "MCAR",
    "rate": 0.15,
    "results": {
      "simple": {
        "ridge_regression": {
          "mae": 0.16542690975449642,
          "rmse": 0.20771474320656944,
          "r2": 0.3994083315168233
        },
        "random_forest": {
          "mae": 0.11637192521636808,
          "rmse": 0.14532977923853715,
          "r2": 0.7059955628477295
        }
      },
      "iterative": {
        "ridge_regression": {
          "mae": 0.1687632814732718,
          "rmse": 0.20661823954732025,
          "r2": 0.4057325119040456
        },
        "random_forest": {
          "mae": 0.11729690267706432,
          "rmse": 0.15316523312652666,
          "r2": 0.6734384492323902
        }
      }
    }
  },
  {
    "dataset": "communities_crime",
    "mechanism": "MCAR",
    "rate": 0.2,
    "results": {
      "simple": {
        "ridge_regression": {
          "mae": 0.17781024443138158,
          "rmse": 0.22540360095828757,
          "r2": 0.29276074667646257
        },
        "random_forest": {
          "mae": 0.12181630235687703,
          "rmse": 0.149765484744595,
          "r2": 0.6877746722046167
        }
      },
      "iterative": {
        "ridge_regression": {
          "mae": 0.1609545559210697,
          "rmse": 0.2129864084687133,
          "r2": 0.3685362306912747
        },
        "random_forest": {
          "mae": 0.12063171143786768,
          "rmse": 0.15827597199732818,
          "r2": 0.6512817827721564
        }
      }
    }
  },
  {
    "dataset": "communities_crime",
    "mechanism": "MCAR",
    "rate": 0.25,
    "results": {
      "simple": {
        "ridge_regression": {
          "mae": 0.17339428474554286,
          "rmse": 0.22046211620936773,
          "r2": 0.3234302114545484
        },
        "random_forest": {
          "mae": 0.14010540084815093,
          "rmse": 0.17317630488182595,
          "r2": 0.5825335347825762
        }
      },
      "iterative": {
        "ridge_regression": {
          "mae": 0.17387061390499142,
          "rmse": 0.21175940135476226,
          "r2": 0.37579095379537686
        },
        "random_forest": {
          "mae": 0.1151329206141081,
          "rmse": 0.15343296114062022,
          "r2": 0.6722958128018812
        }
      }
    }
  },
  {
    "dataset": "communities_crime",
    "mechanism": "MCAR",
    "rate": 0.3,
    "results": {
      "simple": {
        "ridge_regression": {
          "mae": 0.21858631392810846,
          "rmse": 0.27546854514636293,
          "r2": -0.056303424849618366
        },
        "random_forest": {
          "mae": 0.1306979042456789,
          "rmse": 0.15582333164344184,
          "r2": 0.6620055036222474
        }
      },
      "iterative": {
        "ridge_regression": {
          "mae": 0.1757597473129579,
          "rmse": 0.21926815730249014,
          "r2": 0.33073857937838447
        },
        "random_forest": {
          "mae": 0.10760854558635807,
          "rmse": 0.14345728958757878,
          "r2": 0.7135229079260166
        }
      }
    }
  },
  {
    "dataset": "communities_crime",
    "mechanism": "MAR",
    "rate": 0.01,
    "results": {
      "simple": {
        "ridge_regression": {
          "mae": 0.18133119673523096,
          "rmse": 0.23196555029007987,
          "r2": 0.2509830590140236
        },
        "random_forest": {
          "mae": 0.10684676113364291,
          "rmse": 0.14442404444928825,
          "r2": 0.7096487749043716
        }
      },
      "iterative": {
        "ridge_regression": {
          "mae": 0.15813799091359534,
          "rmse": 0.20806672241863597,
          "r2": 0.39737116374139303
        },
        "random_forest": {
          "mae": 0.10802763694690692,
          "rmse": 0.14498148544254982,
          "r2": 0.707403081904245
        }
      }
    }
  },
  {
    "dataset": "communities_crime",
    "mechanism": "MAR",
    "rate": 0.05,
    "results": {
      "simple": {
        "ridge_regression": {
          "mae": 0.16354352077934503,
          "rmse": 0.2024408395712285,
          "r2": 0.4295193520195104
        },
        "random_forest": {
          "mae": 0.10872400099808815,
          "rmse": 0.13840682700096404,
          "r2": 0.7333388902368987
        }
      },
      "iterative": {
        "ridge_regression": {
          "mae": 0.16789688185855317,
          "rmse": 0.20831088019614105,
          "r2": 0.3959560133997275
        },
        "random_forest": {
          "mae": 0.11174210110283421,
          "rmse": 0.1457887011098803,
          "r2": 0.7041358187520326
        }
      }
    }
  },
  {
    "dataset": "communities_crime",
    "mechanism": "MAR",
    "rate": 0.1,
    "results": {
      "simple": {
        "ridge_regression": {
          "mae": 0.18056384013749457,
          "rmse": 0.22808515202217414,
          "r2": 0.2758330741326771
        },
        "random_forest": {
          "mae": 0.11387952472325306,
          "rmse": 0.14251298991101113,
          "r2": 0.7172819345178578
        }
      },
      "iterative": {
        "ridge_regression": {
          "mae": 0.1831708218901226,
          "rmse": 0.22739363081907144,
          "r2": 0.2802175563138989
        },
        "random_forest": {
          "mae": 0.10744771213797778,
          "rmse": 0.14210419026605423,
          "r2": 0.7189015662566417
        }
      }
    }
  },
  {
    "dataset": "communities_crime",
    "mechanism": "MAR",
    "rate": 0.15,
    "results": {
      "simple": {
        "ridge_regression": {
          "mae": 0.15361431150072577,
          "rmse": 0.20126132386079712,
          "r2": 0.4361477635450023
        },
        "random_forest": {
          "mae": 0.10273296451021405,
          "rmse": 0.14080255297648528,
          "r2": 0.7240275584247822
        }
      },
      "iterative": {
        "ridge_regression": {
          "mae": 0.1487198985990787,
          "rmse": 0.19062034345131035,
          "r2": 0.49419495984226414
        },
        "random_forest": {
          "mae": 0.10881044420550853,
          "rmse": 0.14572189200746294,
          "r2": 0.7044069219466993
        }
      }
    }
  },
  {
    "dataset": "communities_crime",
    "mechanism": "MAR",
    "rate": 0.2,
    "results": {
      "simple": {
        "ridge_regression": {
          "mae": 0.20604999554945905,
          "rmse": 0.2493545613547028,
          "r2": 0.13447564849334848
        },
        "random_forest": {
          "mae": 0.12170853483703117,
          "rmse": 0.15674271869281278,
          "r2": 0.6580052747136592
        }
      },
      "iterative": {
        "ridge_regression": {
          "mae": 0.15135045435667935,
          "rmse": 0.19397678992554215,
          "r2": 0.4762256901900357
        },
        "random_forest": {
          "mae": 0.10798785633476225,
          "rmse": 0.14453608299360288,
          "r2": 0.709198113843302
        }
      }
    }
  },
  {
    "dataset": "communities_crime",
    "mechanism": "MAR",
    "rate": 0.25,
    "results": {
      "simple": {
        "ridge_regression": {
          "mae": 0.22556129067604655,
          "rmse": 0.2978215321966474,
          "r2": -0.23468691165063782
        },
        "random_forest": {
          "mae": 0.10892324559304001,
          "rmse": 0.1466070181906206,
          "r2": 0.7008051052029254
        }
      },
      "iterative": {
        "ridge_regression": {
          "mae": 0.15859555801818842,
          "rmse": 0.20555469847818814,
          "r2": 0.41183459891746377
        },
        "random_forest": {
          "mae": 0.10657971048239516,
          "rmse": 0.1424020514214252,
          "r2": 0.717721923988144
        }
      }
    }
  },
  {
    "dataset": "communities_crime",
    "mechanism": "MAR",
    "rate": 0.3,
    "results": {
      "simple": {
        "ridge_regression": {
          "mae": 0.14983228361396456,
          "rmse": 0.19799141092874348,
          "r2": 0.4543208522192499
        },
        "random_forest": {
          "mae": 0.11898357827049849,
          "rmse": 0.14877150154471477,
          "r2": 0.6919053549984988
        }
      },
      "iterative": {
        "ridge_regression": {
          "mae": 0.14890212750245158,
          "rmse": 0.19488921874924595,
          "r2": 0.4712866377652135
        },
        "random_forest": {
          "mae": 0.10579843298706043,
          "rmse": 0.14412879708010007,
          "r2": 0.7108346966951438
        }
      }
    }
  },
  {
    "dataset": "communities_crime",
    "mechanism": "MNAR",
    "rate": 0.01,
    "results": {
      "simple": {
        "ridge_regression": {
          "mae": 0.16720233665724113,
          "rmse": 0.21288764102971086,
          "r2": 0.36912174785084584
        },
        "random_forest": {
          "mae": 0.10483558252679716,
          "rmse": 0.1411152232312057,
          "r2": 0.7228005326498049
        }
      },
      "iterative": {
        "ridge_regression": {
          "mae": 0.15699075204048274,
          "rmse": 0.20510003312887937,
          "r2": 0.414433641204603
        },
        "random_forest": {
          "mae": 0.10563967794529106,
          "rmse": 0.14271628011903492,
          "r2": 0.7164747827395392
        }
      }
    }
  },
  {
    "dataset": "communities_crime",
    "mechanism": "MNAR",
    "rate": 0.05,
    "results": {
      "simple": {
        "ridge_regression": {
          "mae": 0.1688036128437085,
          "rmse": 0.21477396124873036,
          "r2": 0.35789225001390057
        },
        "random_forest": {
          "mae": 0.1150859672852732,
          "rmse": 0.15446383828990207,
          "r2": 0.6678774970957815
        }
      },
      "iterative": {
        "ridge_regression": {
          "mae": 0.1557021515432078,
          "rmse": 0.19899496130341382,
          "r2": 0.44877511313367446
        },
        "random_forest": {
          "mae": 0.11402163468552484,
          "rmse": 0.14690435348725,
          "r2": 0.6995902736691068
        }
      }
    }
  },
  {
    "dataset": "communities_crime",
    "mechanism": "MNAR",
    "rate": 0.1,
    "results": {
      "simple": {
        "ridge_regression": {
          "mae": 0.17112188533396935,
          "rmse": 0.21769002653865432,
          "r2": 0.34033761317814115
        },
        "random_forest": {
          "mae": 0.10420569832509897,
          "rmse": 0.1412880429469367,
          "r2": 0.7221211606258907
        }
      },
      "iterative": {
        "ridge_regression": {
          "mae": 0.15288322231450063,
          "rmse": 0.18917836181170375,
          "r2": 0.5018185206331758
        },
        "random_forest": {
          "mae": 0.10686640173879486,
          "rmse": 0.1443594719157067,
          "r2": 0.7099083511126696
        }
      }
    }
  },
  {
    "dataset": "communities_crime",
    "mechanism": "MNAR",
    "rate": 0.15,
    "results": {
      "simple": {
        "ridge_regression": {
          "mae": 0.14075184422914017,
          "rmse": 0.18389145090554848,
          "r2": 0.5292744885174159
        },
        "random_forest": {
          "mae": 0.105242771451112,
          "rmse": 0.13678650955669405,
          "r2": 0.7395459035752765
        }
      },
      "iterative": {
        "ridge_regression": {
          "mae": 0.1412898486387948,
          "rmse": 0.1809876121111269,
          "r2": 0.5440236083511223
        },
        "random_forest": {
          "mae": 0.10399832962171435,
          "rmse": 0.13853440441318352,
          "r2": 0.7328470703735166
        }
      }
    }
  },
  {
    "dataset": "communities_crime",
    "mechanism": "MNAR",
    "rate": 0.2,
    "results": {
      "simple": {
        "ridge_regression": {
          "mae": 0.1766649673858509,
          "rmse": 0.2254170500434223,
          "r2": 0.2926763469183883
        },
        "random_forest": {
          "mae": 0.10905019750880422,
          "rmse": 0.14379396693840846,
          "r2": 0.712176674109519
        }
      },
      "iterative": {
        "ridge_regression": {
          "mae": 0.17740804787026385,
          "rmse": 0.21914409576350946,
          "r2": 0.3314956990061708
        },
        "random_forest": {
          "mae": 0.11154144118884926,
          "rmse": 0.14568434488558327,
          "r2": 0.7045592290478224
        }
      }
    }
  },
  {
    "dataset": "communities_crime",
    "mechanism": "MNAR",
    "rate": 0.25,
    "results": {
      "simple": {
        "ridge_regression": {
          "mae": 0.19100910821796496,
          "rmse": 0.237621229500442,
          "r2": 0.21401341341522795
        },
        "random_forest": {
          "mae": 0.11951762455516227,
          "rmse": 0.1545160261547682,
          "r2": 0.6676530343016889
        }
      },
      "iterative": {
        "ridge_regression": {
          "mae": 0.17642232672813302,
          "rmse": 0.23003791171338311,
          "r2": 0.26338002746970723
        },
        "random_forest": {
          "mae": 0.11511624059304665,
          "rmse": 0.15027522108223215,
          "r2": 0.6856456978503216
        }
      }
    }
  },
  {
    "dataset": "communities_crime",
    "mechanism": "MNAR",
    "rate": 0.3,
    "results": {
      "simple": {
        "ridge_regression": {
          "mae": 0.21283159606424815,
          "rmse": 0.2466558899822823,
          "r2": 0.1531087644559429
        },
        "random_forest": {
          "mae": 0.11594772633802257,
          "rmse": 0.15072116089870255,
          "r2": 0.6837772448268169
        }
      },
      "iterative": {
        "ridge_regression": {
          "mae": 0.1483395288746367,
          "rmse": 0.1931503771243103,
          "r2": 0.4806791274924572
        },
        "random_forest": {
          "mae": 0.12266042195785808,
          "rmse": 0.15770105075732024,
          "r2": 0.6538105480143768
        }
      }
    }
  }
]